artiruno/__init__.py
artiruno/__main__.py
artiruno/_version.py
artiruno/interactive.py
artiruno/preorder.py
artiruno/util.py
artiruno/vda.py
artiruno/web.py
artiruno-0.4.2.dist-info/METADATA
artiruno-0.4.2.dist-info/WHEEL
artiruno-0.4.2.dist-info/top_level.txt
artiruno-0.4.2.dist-info/RECORD
