Metadata-Version: 2.1
Name: artiruno
Version: 0.4.2
Summary: Verbal decision analysis
Home-page: https://arfer.net/projects/artiruno
Author: Kodi B. Arfer
Project-URL: Documentation, https://arfer.net/projects/artiruno/doc
Project-URL: Source Code, https://github.com/Kodiologist/Artiruno
Classifier: Programming Language :: Python :: 3
Classifier: License :: OSI Approved :: GNU General Public License v3 or later (GPLv3+)
Classifier: Operating System :: OS Independent
Classifier: Topic :: Scientific/Engineering
Classifier: Topic :: Scientific/Engineering :: Mathematics
Requires-Python: >=3.8
